apap/__init__.py
apap/client.py
apap/method.py
apap-0.0.0b3.dist-info/WHEEL
apap-0.0.0b3.dist-info/METADATA
apap-0.0.0b3.dist-info/RECORD
